ondemand/__init__.py
ondemand/client.py
ondemand/config.py
ondemand/errors.py
ondemand/http.py
ondemand_wrapper-0.1.3.dist-info/METADATA
ondemand_wrapper-0.1.3.dist-info/WHEEL
ondemand_wrapper-0.1.3.dist-info/top_level.txt
ondemand_wrapper-0.1.3.dist-info/RECORD
