Metadata-Version: 2.4
Name: ondemand-wrapper
Version: 0.1.3
Summary: Async-first Python SDK for On-Demand APIs
Author-email: RumbleJack56 <ujjwalkakar2005@gmail.com>
License: MIT
Project-URL: Homepage, https://github.com/RumbleJack56/ondemand
Project-URL: Issues, https://github.com/RumbleJack56/ondemand/issues
Classifier: Programming Language :: Python :: 3
Classifier: License :: OSI Approved :: MIT License
Classifier: Operating System :: OS Independent
Requires-Python: >=3.9
Requires-Dist: httpx<0.27.0,>=0.26.0
Requires-Dist: anyio<4.0.0,>=3.7.0
